build/lib/build/lib/build/lib/build/lib/test/basic/test_Map.py
build/lib/build/lib/build/lib/build/lib/test/basic/test_mongo.py
build/lib/build/lib/build/lib/build/lib/test/basic/test_mysql.py
build/lib/build/lib/build/lib/build/lib/test/models/Account.py
build/lib/build/lib/build/lib/build/lib/test/models/Group.py
build/lib/build/lib/build/lib/build/lib/test/models/Record.py
build/lib/build/lib/build/lib/build/lib/test/models/Recorder.py
build/lib/build/lib/build/lib/build/lib/test/models/User.py
build/lib/build/lib/build/lib/build/lib/torm/__init__.py
build/lib/build/lib/build/lib/build/lib/torm/builder/BaseBuilder.py
build/lib/build/lib/build/lib/build/lib/torm/builder/MongoBuilder.py
build/lib/build/lib/build/lib/build/lib/torm/builder/MysqlBuilder.py
build/lib/build/lib/build/lib/build/lib/torm/builder/__init__.py
build/lib/build/lib/build/lib/build/lib/torm/connection/Connection.py
build/lib/build/lib/build/lib/build/lib/torm/connection/ConnectionMetaClass.py
build/lib/build/lib/build/lib/build/lib/torm/connection/MongoConnecction.py
build/lib/build/lib/build/lib/build/lib/torm/connection/MysqlConnection.py
build/lib/build/lib/build/lib/build/lib/torm/connection/__init__.py
build/lib/build/lib/build/lib/build/lib/torm/connection/Pool/MysqlConnectionPool.py
build/lib/build/lib/build/lib/build/lib/torm/connection/Pool/__init__.py
build/lib/build/lib/build/lib/build/lib/torm/field/Bool.py
build/lib/build/lib/build/lib/build/lib/torm/field/Dict.py
build/lib/build/lib/build/lib/build/lib/torm/field/DictList.py
build/lib/build/lib/build/lib/build/lib/torm/field/Email.py
build/lib/build/lib/build/lib/build/lib/torm/field/EmailList.py
build/lib/build/lib/build/lib/build/lib/torm/field/Field.py
build/lib/build/lib/build/lib/build/lib/torm/field/Float.py
build/lib/build/lib/build/lib/build/lib/torm/field/Int.py
build/lib/build/lib/build/lib/build/lib/torm/field/List.py
build/lib/build/lib/build/lib/build/lib/torm/field/Map.py
torm-0.1.9.dist-info/LICENSE
torm-0.1.9.dist-info/METADATA
torm-0.1.9.dist-info/WHEEL
torm-0.1.9.dist-info/top_level.txt
torm-0.1.9.dist-info/zip-safe
torm-0.1.9.dist-info/RECORD
