Metadata-Version: 2.1
Name: torm
Version: 0.1.9
Summary: mongodb style python orm.
Home-page: https://github.com/cofepy
Author: Aeneas
Author-email: kai.he@taraxa.io
License: MIT
Keywords: mongodb orm
Platform: UNKNOWN
Classifier: License :: OSI Approved :: MIT License
Classifier: Programming Language :: Python
Classifier: Intended Audience :: Developers
Classifier: Operating System :: OS Independent
Requires-Python: >=3.7
Requires-Dist: pymongo[srv,tls] (==3.9.0)
